{"_id":"beer_Heavy_Seas_Prosit!_Imperial_Oktoberfest_Lager","brewery":"Clipper City Brewing Co.","name":"Heavy Seas Prosit! Imperial Oktoberfest Lager","abv":"9","description":"Malt focused, made with five types of grain including Vienna and Munich malts \u00e2\u0080\u0093 plus a secret extra malt that we use only in our Prosit! Consider this bomber to be the burly big brother to our Clipper City MarzHon, a three year in a row winner at the Great American Beer Festival. We\u00e2\u0080\u0099ve balanced the sweetness of the malt with three kinds of hops making this one of the boldest marzen style lagers you\u00e2\u0080\u0099ll ever try.\r\n\r\n5 Kinds of Malt, 3 Kinds of Hops\r\nestimated ABV 9% estimated IBU 25","category":"German Lager","style":"German-Style Oktoberfest","updated":"2010-07-22 20:00:20"}