{"_id":"beer_St_Patrick's_Ale","brewery":"Strangford Lough Brewing Company Ltd","name":"St Patrick's Ale","abv":"6","description":"A deep copper coloured traditional Irish Ale with highly developed and complex flavours. St Patrick\u00e2\u0080\u0099s Ale\/Dark is brewed with four malts and two hops, carefully married together to complement eachother producing a satisfying full flavour, ending with a Styrian late hop for a truly brilliant finish.","category":"British Ale","style":"Classic English-Style Pale Ale","updated":"2010-07-22 20:00:20"}